{
	"Version": 3,
	"Parameters": [
		{
			"Id": "ParamAngleX",
			"GroupId": "ParamGroup",
			"Name": "角度 X"
		},
		{
			"Id": "ParamAngleY",
			"GroupId": "ParamGroup",
			"Name": "角度 Y"
		},
		{
			"Id": "ParamAngleZ",
			"GroupId": "ParamGroup",
			"Name": "角度 Z"
		},
		{
			"Id": "ParamEyeBallX",
			"GroupId": "ParamGroup2",
			"Name": "眼珠 X"
		},
		{
			"Id": "ParamEyeBallY",
			"GroupId": "ParamGroup2",
			"Name": "眼珠 Y"
		},
		{
			"Id": "ParamMouthForm",
			"GroupId": "ParamGroup2",
			"Name": "嘴　变形"
		},
		{
			"Id": "ParamMouthOpenY",
			"GroupId": "ParamGroup2",
			"Name": "嘴　张开和闭合"
		},
		{
			"Id": "ParamCheek",
			"GroupId": "ParamGroup2",
			"Name": "脸颊泛红"
		},
		{
			"Id": "ParamEyeLOpen",
			"GroupId": "ParamGroup2",
			"Name": "左眼　开闭"
		},
		{
			"Id": "ParamEyeROpen",
			"GroupId": "ParamGroup2",
			"Name": "右眼  开闭"
		},
		{
			"Id": "ParamEyeLSmile",
			"GroupId": "ParamGroup2",
			"Name": "左眼　微笑"
		},
		{
			"Id": "ParamEyeRSmile",
			"GroupId": "ParamGroup2",
			"Name": "右眼　微笑"
		},
		{
			"Id": "ParamBrowRY",
			"GroupId": "ParamGroup7",
			"Name": "右眉　上下"
		},
		{
			"Id": "ParamBrowRAngle",
			"GroupId": "ParamGroup7",
			"Name": "右眉　角度"
		},
		{
			"Id": "ParamBrowRX",
			"GroupId": "ParamGroup7",
			"Name": "右眉　左右"
		},
		{
			"Id": "ParamBrowRForm",
			"GroupId": "ParamGroup7",
			"Name": "右眉　変形"
		},
		{
			"Id": "ParamBrowLY",
			"GroupId": "ParamGroup7",
			"Name": "左眉上下"
		},
		{
			"Id": "ParamBrowLAngle",
			"GroupId": "ParamGroup7",
			"Name": "左眉　角度"
		},
		{
			"Id": "ParamBrowLX",
			"GroupId": "ParamGroup7",
			"Name": "左眉　左右"
		},
		{
			"Id": "ParamBrowLForm",
			"GroupId": "ParamGroup7",
			"Name": "左眉　変形"
		},
		{
			"Id": "ParamBodyAngleX",
			"GroupId": "ParamGroup3",
			"Name": "身体旋转　X"
		},
		{
			"Id": "ParamBodyAngleY",
			"GroupId": "ParamGroup3",
			"Name": "身体旋转　Y"
		},
		{
			"Id": "ParamBodyAngleZ",
			"GroupId": "ParamGroup3",
			"Name": "身体旋转　Z"
		},
		{
			"Id": "ParamBreath",
			"GroupId": "ParamGroup3",
			"Name": "呼吸"
		},
		{
			"Id": "ParamHairBack",
			"GroupId": "ParamGroup4",
			"Name": "摇动 后发"
		},
		{
			"Id": "ParamHairFront",
			"GroupId": "ParamGroup4",
			"Name": "摇动 前发"
		},
		{
			"Id": "ParamHairSide",
			"GroupId": "ParamGroup4",
			"Name": "摇动 侧发"
		},
		{
			"Id": "Param6",
			"GroupId": "ParamGroup6",
			"Name": "睫毛物理l1"
		},
		{
			"Id": "Param5",
			"GroupId": "ParamGroup6",
			"Name": "睫毛物理r1"
		},
		{
			"Id": "Param",
			"GroupId": "ParamGroup5",
			"Name": "眼睛物理r1"
		},
		{
			"Id": "Param2",
			"GroupId": "ParamGroup5",
			"Name": "眼睛物理r2"
		},
		{
			"Id": "Param3",
			"GroupId": "ParamGroup5",
			"Name": "眼睛物理l1"
		},
		{
			"Id": "Param4",
			"GroupId": "ParamGroup5",
			"Name": "眼睛物理l2"
		},
		{
			"Id": "Param7",
			"GroupId": "ParamGroup8",
			"Name": "刘海物理1"
		},
		{
			"Id": "Param8",
			"GroupId": "ParamGroup8",
			"Name": "刘海物理2"
		},
		{
			"Id": "Param9",
			"GroupId": "ParamGroup8",
			"Name": "刘海物理3"
		},
		{
			"Id": "Param10",
			"GroupId": "ParamGroup8",
			"Name": "侧发物理1"
		},
		{
			"Id": "Param11",
			"GroupId": "ParamGroup8",
			"Name": "侧发物理2"
		},
		{
			"Id": "Param12",
			"GroupId": "ParamGroup8",
			"Name": "侧发物理3"
		},
		{
			"Id": "Param19",
			"GroupId": "ParamGroup8",
			"Name": "麻花辫物理1"
		},
		{
			"Id": "Param20",
			"GroupId": "ParamGroup8",
			"Name": "麻花辫物理2"
		},
		{
			"Id": "Param21",
			"GroupId": "ParamGroup8",
			"Name": "麻花辫物理3"
		},
		{
			"Id": "Param22",
			"GroupId": "ParamGroup8",
			"Name": "后发1"
		},
		{
			"Id": "Param23",
			"GroupId": "ParamGroup8",
			"Name": "后发2"
		},
		{
			"Id": "Param24",
			"GroupId": "ParamGroup8",
			"Name": "后发3"
		},
		{
			"Id": "Param15",
			"GroupId": "ParamGroup8",
			"Name": "垂发物理1"
		},
		{
			"Id": "Param16",
			"GroupId": "ParamGroup8",
			"Name": "垂发物理2"
		},
		{
			"Id": "Param17",
			"GroupId": "ParamGroup8",
			"Name": "垂发物理3"
		},
		{
			"Id": "Param18",
			"GroupId": "ParamGroup8",
			"Name": "花物理1"
		},
		{
			"Id": "Param25",
			"GroupId": "ParamGroup8",
			"Name": "花物理2"
		},
		{
			"Id": "Param13",
			"GroupId": "ParamGroup9",
			"Name": "帽子物理1"
		},
		{
			"Id": "Param14",
			"GroupId": "ParamGroup9",
			"Name": "帽子物理2"
		}
	],
	"ParameterGroups": [
		{
			"Id": "ParamGroup",
			"GroupId": "",
			"Name": "角度"
		},
		{
			"Id": "ParamGroup2",
			"GroupId": "",
			"Name": "五官"
		},
		{
			"Id": "ParamGroup7",
			"GroupId": "",
			"Name": "眉毛"
		},
		{
			"Id": "ParamGroup3",
			"GroupId": "",
			"Name": "身体"
		},
		{
			"Id": "ParamGroup4",
			"GroupId": "",
			"Name": "头发"
		},
		{
			"Id": "ParamGroup6",
			"GroupId": "",
			"Name": "睫毛物理"
		},
		{
			"Id": "ParamGroup5",
			"GroupId": "",
			"Name": "眼睛物理"
		},
		{
			"Id": "ParamGroup8",
			"GroupId": "",
			"Name": "前发物理"
		},
		{
			"Id": "ParamGroup9",
			"GroupId": "",
			"Name": "帽子物理"
		}
	],
	"Parts": [
		{
			"Id": "Part14",
			"Name": "广告.png"
		},
		{
			"Id": "Part",
			"Name": "帽子"
		},
		{
			"Id": "Part2",
			"Name": "眉毛"
		},
		{
			"Id": "Part3",
			"Name": "前发"
		},
		{
			"Id": "Part4",
			"Name": "左眼"
		},
		{
			"Id": "Part5",
			"Name": "右眼"
		},
		{
			"Id": "Part6",
			"Name": "鼻子"
		},
		{
			"Id": "Part7",
			"Name": "嘴巴"
		},
		{
			"Id": "Part8",
			"Name": "脸"
		},
		{
			"Id": "Part9",
			"Name": "耳朵"
		},
		{
			"Id": "Part10",
			"Name": "垂发"
		},
		{
			"Id": "Part11",
			"Name": "身子"
		},
		{
			"Id": "Part12",
			"Name": "后发"
		},
		{
			"Id": "Part13",
			"Name": "帽子里"
		}
	],
	"CombinedParameters": [
		[
			"ParamAngleX",
			"ParamAngleY"
		],
		[
			"Param",
			"Param2"
		],
		[
			"Param18",
			"Param25"
		],
		[
			"Param13",
			"Param14"
		]
	]
}